dltrain/__init__.py
dltrain/checkpoint.py
dltrain/dataset.py
dltrain/delineator.py
dltrain/error.py
dltrain/evaluation.py
dltrain/forward.py
dltrain/inject.py
dltrain/options.py
dltrain/train.py
dltrain/transform.py
dltrain/utils.py
dltrain/builder/__init__.py
dltrain/builder/base.py
dltrain/builder/builder.py
dltrain/builder/core.py
dltrain/builder/criterion.py
dltrain/builder/dataset.py
dltrain/builder/delineator.py
dltrain/builder/evaluation.py
dltrain/builder/forward.py
dltrain/builder/inject.py
dltrain/builder/model.py
dltrain/builder/optimizer.py
dltrain/builder/scheduler.py
dltrain/builder/transforms.py
dltrain/models/__init__.py
dltrain/models/builder.py
dltrain/models/component.py
dltrain/models/model.py
dltrain/models/wrapper.py
dltrain-0.1.4.dist-info/LICENSE
dltrain-0.1.4.dist-info/METADATA
dltrain-0.1.4.dist-info/WHEEL
dltrain-0.1.4.dist-info/top_level.txt
dltrain-0.1.4.dist-info/RECORD
